README.txt
bootstrap.py
buildout.cfg
setup.py
docs/AUTHORS.txt
docs/CHANGES.txt
docs/LICENSE.txt
docs/REQUIREMENTS.txt
src/Products/__init__.py
src/Products.ATCountryWidget.egg-info/PKG-INFO
src/Products.ATCountryWidget.egg-info/SOURCES.txt
src/Products.ATCountryWidget.egg-info/dependency_links.txt
src/Products.ATCountryWidget.egg-info/namespace_packages.txt
src/Products.ATCountryWidget.egg-info/not-zip-safe
src/Products.ATCountryWidget.egg-info/requires.txt
src/Products.ATCountryWidget.egg-info/top_level.txt
src/Products/ATCountryWidget/ATCWDemoType.py
src/Products/ATCountryWidget/CountryTool.py
src/Products/ATCountryWidget/Interfaces.py
src/Products/ATCountryWidget/Widget.py
src/Products/ATCountryWidget/__init__.py
src/Products/ATCountryWidget/config.py
src/Products/ATCountryWidget/refresh.txt
src/Products/ATCountryWidget/utils.py
src/Products/ATCountryWidget/validators.py
src/Products/ATCountryWidget/version.txt
src/Products/ATCountryWidget/Extensions/Install.py
src/Products/ATCountryWidget/i18n/atcw-de.po
src/Products/ATCountryWidget/i18n/atcw-nl.po
src/Products/ATCountryWidget/i18n/atcw.pot
src/Products/ATCountryWidget/skins/ATCountryWidget/country_widgets/area.pt
src/Products/ATCountryWidget/skins/ATCountryWidget/country_widgets/country.pt
src/Products/ATCountryWidget/skins/ATCountryWidget/country_widgets/multicountry.pt
src/Products/ATCountryWidget/tests/TestWidget.py
src/Products/ATCountryWidget/tests/__init__.py
src/Products/ATCountryWidget/tests/test_util.py
src/Products/ATCountryWidget/tests/test_validator.py
src/Products/ATCountryWidget/tests/test_widgets.py
src/Products/ATCountryWidget/www/CountryUtilCountries.zpt
src/Products/ATCountryWidget/www/CountryUtilInfo.zpt
src/Products/ATCountryWidget/www/tool.gif