Metadata-Version: 1.0
Name: Products.ATCountryWidget
Version: 0.2.6
Summary: A country widget for Archetypes
Home-page: http://pypi.python.org/pypi/Products.ATCountryWidget
Author: Daniel Havlik
Author-email: dh@gocept.com
License: ZPL 2.1
Keywords: archetypes plone
Platform: UNKNOWN
